setup.py
code/__init__.py
zihaothird.egg-info/PKG-INFO
zihaothird.egg-info/SOURCES.txt
zihaothird.egg-info/dependency_links.txt
zihaothird.egg-info/entry_points.txt
zihaothird.egg-info/top_level.txt