Metadata-Version: 1.0
Name: zihaothird
Version: 0.0.1
Summary: 吃枣药丸
Home-page: https://zhuanlan.zhihu.com/p/26159930
Author: xlzd
Author-email: 123@qq.com
License: UNKNOWN
Platform: UNKNOWN
